pokerbot/__init__.py
pokerbot/__main__.py
pokerbot/ai.py
pokerbot/app.py
pokerbot/classifiers.py
pokerbot/functions.py
pokerbot/models.py
pokerbot/states.py
pokerbot/systems.py
pokerbot/commands/__init__.py
pokerbot/commands/ai.py
pokerbot/commands/testing.py
pokerbot/tools/__init__.py
pokerbot-0.0.1.dist-info/METADATA
pokerbot-0.0.1.dist-info/WHEEL
pokerbot-0.0.1.dist-info/entry_points.txt
pokerbot-0.0.1.dist-info/RECORD
